modular_mcp/__init__.py
modular_mcp/bundle.py
modular_mcp/modular_mcp.py
modular_mcp/managers/__init__.py
modular_mcp/managers/prompt.py
modular_mcp/managers/resource.py
modular_mcp/managers/tool.py
modular_mcp-0.3.0.dist-info/METADATA
modular_mcp-0.3.0.dist-info/WHEEL
modular_mcp-0.3.0.dist-info/RECORD
